albylib/__about__.py
albylib/__init__.py
albylib/io.py
albylib/octopus.py
albylib/pandas.py
albylib/subprocess.py
albylib/machine_learning/__init__.py
albylib/machine_learning/sklearn.py
albylib-0.2.4.dist-info/METADATA
albylib-0.2.4.dist-info/WHEEL
albylib-0.2.4.dist-info/RECORD
