Metadata-Version: 2.3
Name: albylib
Version: 0.2.4
Summary: A bunch of utility functions
Project-URL: Documentation, https://github.com/unknown/albylib#readme
Project-URL: Issues, https://github.com/unknown/albylib/issues
Project-URL: Source, https://github.com/unknown/albylib
Author-email: Albert Lee <grepinsight@gmail.com>
License-Expression: MIT
Classifier: Development Status :: 4 - Beta
Classifier: Programming Language :: Python
Classifier: Programming Language :: Python :: 3.7
Classifier: Programming Language :: Python :: 3.8
Classifier: Programming Language :: Python :: 3.9
Classifier: Programming Language :: Python :: 3.10
Classifier: Programming Language :: Python :: 3.11
Classifier: Programming Language :: Python :: Implementation :: CPython
Classifier: Programming Language :: Python :: Implementation :: PyPy
Requires-Python: >=3.7
